MANIFEST.in
Makefile
README.md
setup.py
./MinkowskiEngine/MinkowskiBroadcast.py
./MinkowskiEngine/MinkowskiChannelwiseConvolution.py
./MinkowskiEngine/MinkowskiCommon.py
./MinkowskiEngine/MinkowskiConvolution.py
./MinkowskiEngine/MinkowskiCoordinateManager.py
./MinkowskiEngine/MinkowskiFunctional.py
./MinkowskiEngine/MinkowskiInterpolation.py
./MinkowskiEngine/MinkowskiKernelGenerator.py
./MinkowskiEngine/MinkowskiNetwork.py
./MinkowskiEngine/MinkowskiNonlinearity.py
./MinkowskiEngine/MinkowskiNormalization.py
./MinkowskiEngine/MinkowskiOps.py
./MinkowskiEngine/MinkowskiPooling.py
./MinkowskiEngine/MinkowskiPruning.py
./MinkowskiEngine/MinkowskiSparseTensor.py
./MinkowskiEngine/MinkowskiTensor.py
./MinkowskiEngine/MinkowskiTensorField.py
./MinkowskiEngine/MinkowskiUnion.py
./MinkowskiEngine/__init__.py
./MinkowskiEngine/diagnostics.py
./MinkowskiEngine/sparse_matrix_functions.py
./MinkowskiEngine/modules/__init__.py
./MinkowskiEngine/modules/resnet_block.py
./MinkowskiEngine/modules/senet_block.py
./MinkowskiEngine/utils/__init__.py
./MinkowskiEngine/utils/collation.py
./MinkowskiEngine/utils/coords.py
./MinkowskiEngine/utils/gradcheck.py
./MinkowskiEngine/utils/init.py
./MinkowskiEngine/utils/quantization.py
./MinkowskiEngine/utils/summary.py
./MinkowskiEngine/utils/torchsummary.py
/home/chrischoy/projects/MinkowskiEngine/src/broadcast_cpu.cpp
/home/chrischoy/projects/MinkowskiEngine/src/broadcast_gpu.cu
/home/chrischoy/projects/MinkowskiEngine/src/broadcast_kernel.cu
/home/chrischoy/projects/MinkowskiEngine/src/convolution_cpu.cpp
/home/chrischoy/projects/MinkowskiEngine/src/convolution_gpu.cu
/home/chrischoy/projects/MinkowskiEngine/src/convolution_kernel.cu
/home/chrischoy/projects/MinkowskiEngine/src/convolution_transpose_cpu.cpp
/home/chrischoy/projects/MinkowskiEngine/src/convolution_transpose_gpu.cu
/home/chrischoy/projects/MinkowskiEngine/src/coordinate_map_gpu.cu
/home/chrischoy/projects/MinkowskiEngine/src/coordinate_map_manager.cpp
MinkowskiEngine.egg-info/PKG-INFO
MinkowskiEngine.egg-info/SOURCES.txt
MinkowskiEngine.egg-info/dependency_links.txt
MinkowskiEngine.egg-info/not-zip-safe
MinkowskiEngine.egg-info/requires.txt
MinkowskiEngine.egg-info/top_level.txt
