Metadata-Version: 2.1
Name: MinkowskiEngine
Version: 0.5.4
Summary: a convolutional neural network library for sparse tensors
Home-page: https://github.com/NVIDIA/MinkowskiEngine
Author: Christopher Choy
Author-email: chrischoy@ai.stanford.edu
License: UNKNOWN
Keywords: pytorch,Minkowski Engine,Sparse Tensor,Convolutional Neural Networks,3D Vision,Deep Learning
Platform: UNKNOWN
Classifier: Environment :: Console
Classifier: Development Status :: 3 - Alpha
Classifier: Intended Audience :: Developers
Classifier: Intended Audience :: Other Audience
Classifier: Intended Audience :: Science/Research
Classifier: License :: OSI Approved :: MIT License
Classifier: Natural Language :: English
Classifier: Programming Language :: C++
Classifier: Programming Language :: Python :: 3.6
Classifier: Programming Language :: Python :: 3.7
Classifier: Programming Language :: Python :: 3.8
Classifier: Topic :: Multimedia :: Graphics
Classifier: Topic :: Scientific/Engineering
Classifier: Topic :: Scientific/Engineering :: Artificial Intelligence
Classifier: Topic :: Scientific/Engineering :: Mathematics
Classifier: Topic :: Scientific/Engineering :: Physics
Classifier: Topic :: Scientific/Engineering :: Visualization
Requires-Python: >=3.6
